leonSec/__init__.py
leonSec/leonSec.py
leontestA-0.1.0.dist-info/LICENCE.txt
leontestA-0.1.0.dist-info/METADATA
leontestA-0.1.0.dist-info/WHEEL
leontestA-0.1.0.dist-info/top_level.txt
leontestA-0.1.0.dist-info/RECORD
